tigerblog/default_config.json
tigerblog/tigerblog.py
tigerblog/themes/beautiful-tiger/contact.html
tigerblog/themes/beautiful-tiger/footer.html
tigerblog/themes/beautiful-tiger/intro.html
tigerblog/themes/beautiful-tiger/javascript.html
tigerblog/themes/beautiful-tiger/listing.html
tigerblog/themes/beautiful-tiger/macros.html
tigerblog/themes/beautiful-tiger/navbar.html
tigerblog/themes/beautiful-tiger/post.html
tigerblog/themes/beautiful-tiger/redirect.html
tigerblog/themes/beautiful-tiger/related-blogs.html
tigerblog/themes/beautiful-tiger/seo_tags_listings.html
tigerblog/themes/beautiful-tiger/seo_tags_post.html
tigerblog/themes/beautiful-tiger/share-page-section.html
tigerblog/themes/beautiful-tiger/sidebar.html
tigerblog/themes/beautiful-tiger/sitemap.xml
tigerblog/themes/beautiful-tiger/static/css/custom-css.css
tigerblog/themes/beautiful-tiger/static/css/single-blog.css
tigerblog/themes/beautiful-tiger/static/css/style.css
tigerblog/themes/beautiful-tiger/static/images/aside-logo.svg
tigerblog/themes/beautiful-tiger/static/images/favicon.ico
tigerblog/themes/beautiful-tiger/static/images/linkedin.png
tigerblog/themes/beautiful-tiger/static/images/logo-white.png
tigerblog/themes/beautiful-tiger/static/images/logo.jpg
tigerblog/themes/beautiful-tiger/static/images/medium.png
tigerblog/themes/beautiful-tiger/static/images/nav-logo.svg
tigerblog/themes/beautiful-tiger/static/images/reddit.png
tigerblog/themes/beautiful-tiger/static/images/twitter.png
tigerblog/themes/beautiful-tiger/static/images/youtube.png
tigerblog/themes/beautiful-tiger/static/js/lazyload.js
tigerblog-0.1.40.dist-info/LICENSE.txt
tigerblog-0.1.40.dist-info/METADATA
tigerblog-0.1.40.dist-info/WHEEL
tigerblog-0.1.40.dist-info/entry_points.txt
tigerblog-0.1.40.dist-info/top_level.txt
tigerblog-0.1.40.dist-info/zip-safe
tigerblog-0.1.40.dist-info/RECORD
