Metadata-Version: 2.1
Name: tigerblog
Version: 0.1.40
Summary: Simplest Blog Engine for Developers
Home-page: https://github.com/tigerteamx/tigerblog
Author: Martin F
Author-email: pypi.org@tigerteamx.com
Keywords: blog,productivity,bottlepy,peewee
Classifier: Programming Language :: Python :: 3
Classifier: License :: OSI Approved :: MIT License
Classifier: Operating System :: OS Independent
Requires-Python: >=3.8
License-File: LICENSE.txt
Requires-Dist: Jinja2 ==3.1.2
Requires-Dist: python-slugify ==7.0.0
Requires-Dist: python-frontmatter ==1.0.0
Requires-Dist: docopt ==0.6.2
Requires-Dist: Markdown ==3.4.1
Requires-Dist: htmlmin ==0.1.12
Requires-Dist: Pillow ==9.0.1
